LICENSE
README.md
setup.py
src/biotsavart/__init__.py
src/biotsavart/biotsavart.py
src/biotsavartlaw.egg-info/PKG-INFO
src/biotsavartlaw.egg-info/SOURCES.txt
src/biotsavartlaw.egg-info/dependency_links.txt
src/biotsavartlaw.egg-info/requires.txt
src/biotsavartlaw.egg-info/top_level.txt
tests/test_physics.py