Metadata-Version: 2.1
Name: biotsavartlaw
Version: 0.0.1
Summary: generate magnetic fields in free space using biot savart law
Author: Matthew P. Griffiths
Author-email: mpg@geo.au.dk
License: MIT
Requires-Python: >=3.8
License-File: LICENSE
Requires-Dist: numpy
Requires-Dist: matplotlib
